<?xml version="1.0"?>
<liturgia> <ligne id="0">
<la>Ioannes (5,33-36)
</la></ligne>
<ligne id="1">
<la>In illo tempore: Dixit Iesus Iudaeis: Vos mis&#xED;stis ad Io&#xE1;nnem, et testim&#xF3;nium perh&#xED;buit verit&#xE1;ti; ego autem non ab h&#xF3;mine testim&#xF3;nium acc&#xED;pio, sed haec dico, ut vos salvi sitis. Ille erat luc&#xE9;rna ardens et lucens; vos autem volu&#xED;stis exsult&#xE1;re ad horam in luce e&#xED;us. Ego autem h&#xE1;beo testim&#xF3;nium ma&#xED;us Io&#xE1;nne; &#xF3;pera enim, quae dedit mihi Pater, ut perf&#xED;ciam ea, ipsa &#xF3;pera, quae ego f&#xE1;cio, testim&#xF3;nium p&#xE9;rhibent de me, quia Pater me misit.</la></ligne>
</liturgia>
