<?xml version="1.0"?>
<liturgia> <ligne id="0">
<la>Luc (21,5-11)
</la></ligne>
<ligne id="1">
<la>In illo tempore: Quib&#xFA;sdam dic&#xE9;ntibus de templo, quod lap&#xED;dibus bonis et donis orn&#xE1;tum, esset dixit:&#xA0;&#x201C;Haec quae vid&#xE9;tis, v&#xE9;nient dies, in quibus non relinqu&#xE9;tur lapis super l&#xE1;pidem, qui non destru&#xE1;tur.&#x201D; Interrogav&#xE9;runt autem illum dic&#xE9;ntes: &#x201C;Praec&#xE9;ptor, quando ergo haec erunt, et quod signum, cum f&#xED;eri inc&#xED;pient?&#x201D;&#xA0;Qui dixit: &#x201C;Vid&#xE9;te, ne seduc&#xE1;mini. Multi enim v&#xE9;nient in n&#xF3;mine meo dic&#xE9;ntes: &#x2018;Ego sum&#x2019; et: &#x2018;T&#xE9;mpus appropinqu&#xE1;vit.&#x2019; Nol&#xED;te ergo ire post illos.&#xA0;Cum autem audi&#xE9;ritis pr&#xF3;elia et sediti&#xF3;nes, nol&#xED;te terr&#xE9;ri; op&#xF3;rtet enim primum haec f&#xED;eri, sed non statim finis.&#x201D; Tunc dic&#xE9;bat illis: &#x201C;S&#xFA;rget gens contra gentem, et regnum adv&#xE9;rsus regnum; et terrae motus magni et per loca fames et pestil&#xE9;ntiae erunt, terror&#xE9;sque et de caelo signa magna erunt.</la></ligne>
</liturgia>
