<?xml version="1.0"?>
<liturgia> <ligne id="0">
<la>Luc (13,31-35)
</la></ligne>
<ligne id="1">
<la>In illa die access&#xE9;runt quidam pharisae&#xF3;rum dic&#xE9;ntes illi: &#x201C;Exi et vade hinc, quia Her&#xF3;des vult te occ&#xED;dere.&#x201D; Et ait illis: &#x201C;Ite, d&#xED;cite vulpi illi: &#x2018;Ecce e&#xED;cio daem&#xF3;nia et sanit&#xE1;tes perf&#xED;cio h&#xF3;die et cras et t&#xE9;rtia cons&#xFA;mmor. Ver&#xFA;mtamen op&#xF3;rtet me h&#xF3;die et cras et sequ&#xE9;nti ambul&#xE1;re, quia non capit proph&#xE9;tam per&#xED;re extra Ierus&#xE1;lem.&#x2019; Ierus&#xE1;lem, Ierus&#xE1;lem, quae occ&#xED;dis proph&#xE9;tas et l&#xE1;pidas eos, qui missi sunt ad te, qu&#xF3;tiens v&#xF3;lui congreg&#xE1;re f&#xED;lios tuos, quem&#xE1;dmodum avis nidum suum sub pinnis, et nolu&#xED;stis.&#xA0;Ecce rel&#xED;nquitur vobis domus vestra. Dico autem vobis: Non vid&#xE9;bitis me, donec v&#xE9;niat cum dic&#xE9;tis: &#x2018;Bened&#xED;ctus, qui venit in n&#xF3;mine D&#xF3;mini.&#x2019;&#x201D;</la></ligne>
</liturgia>
