<?xml version="1.0"?>
<liturgia> <ligne id="0">
<la>Matthaeus (13,1-9)
</la></ligne>
<ligne id="1">
<la>In illo die &#xE9;xiens I&#xE9;sus de domo sed&#xE9;bat secus mare;&#xA0;et congreg&#xE1;tae sunt ad eum turbae multae, ita ut in nav&#xED;culam asc&#xE9;ndens sed&#xE9;ret, et omnis turba stabat in lit&#xF3;re.&#xA0;Et loc&#xFA;tus est eis multa in par&#xE1;bolis dicens: &#x201C;Ecce &#xE9;xiit, qui s&#xE9;minat, semin&#xE1;re. Et dum s&#xE9;minat, quaedam cecid&#xE9;runt secus viam, et ven&#xE9;runt v&#xF3;lucres et comed&#xE9;runt ea.&#xA0;&#xC1;lia autem cecid&#xE9;runt in petr&#xF3;sa, ubi non hab&#xE9;bant terram multam, et cont&#xED;nuo ex&#xF3;rta sunt, quia non hab&#xE9;bant altit&#xFA;dinem terrae; sole autem orto, aestuav&#xE9;runt et, quia non hab&#xE9;bant rad&#xED;cem, aru&#xE9;runt. &#xC1;lia autem cecid&#xE9;runt in spinas, et crev&#xE9;runt spinae et suffocav&#xE9;runt ea. &#xC1;lia vero cecid&#xE9;runt in terram bonam et dabant fructum: &#xE1;liud cent&#xE9;simum, &#xE1;liud sexag&#xE9;simum, &#xE1;liud tric&#xE9;simum.&#xA0;Qui habet aures, &#xE1;udiat.&#x201D;</la></ligne>
</liturgia>
