<?xml version="1.0"?>
<liturgia> <ligne id="0">
<la>Ezechiel (34,11-12.15-17)
</la></ligne>
<ligne id="1">
<la>Haec dicit D&#xF3;minus Deus: Ecce ego ipse requ&#xED;ram oves meas et visit&#xE1;bo eas. Sicut v&#xED;sitat pastor gregem suum in die, quando f&#xFA;erit in m&#xE9;dio &#xF3;vium su&#xE1;rum dissipat&#xE1;rum, sic visit&#xE1;bo oves meas et liber&#xE1;bo eas de &#xF3;mnibus locis, in quibus disp&#xE9;rsae f&#xFA;erant in die nubis et cal&#xED;ginis. Ego pascam oves meas et ego eas accub&#xE1;re f&#xE1;ciam, dicit D&#xF3;minus Deus.&#xA0;Quod per&#xED;erat, requ&#xED;ram et, quod ei&#xE9;ctum erat, red&#xFA;cam et, quod confr&#xE1;ctum f&#xFA;erat, allig&#xE1;bo et, quod inf&#xED;rmum erat, consolid&#xE1;bo et, quod pingue et forte, cust&#xF3;diam et pascam illas in iud&#xED;cio.&#xA0;Vos autem, grex meus, haec dicit D&#xF3;minus Deus: Ecce ego i&#xFA;dico inter pecus et pecus, inter ar&#xED;etes et hircos.</la></ligne>
</liturgia>
