<?xml version="1.0"?>
<liturgia> <ligne id="0">
<la>Ezechiel (3,16-21)
</la></ligne>
<ligne id="1">
<la>In diebus illis: Cum autem pertrans&#xED;ssent septem dies, factum est verbum D&#xF3;mini ad me dicens: &#x201C;Fili h&#xF3;minis, speculat&#xF3;rem dedi te d&#xF3;mui Israel; et &#xE1;udies de ore meo verbum et common&#xE9;bis eos ex me. Si, dic&#xE9;nte me ad &#xED;mpium: Morte mori&#xE9;ris, non common&#xFA;eris eum neque loc&#xFA;tus f&#xFA;eris ei, ut avert&#xE1;tur a via sua &#xED;mpia et vivat, ipse &#xED;mpius in iniquit&#xE1;te sua mori&#xE9;tur, s&#xE1;nguinem autem e&#xED;us de manu tua requ&#xED;ram. Si autem tu common&#xFA;eris &#xED;mpium, et ille non f&#xFA;erit conv&#xE9;rsus ab impiet&#xE1;te sua et a via sua &#xED;mpia, ipse quidem in iniquit&#xE1;te sua mori&#xE9;tur, tu autem &#xE1;nimam tuam liber&#xE1;sti. Sed et si conv&#xE9;rsus i&#xFA;stus a iust&#xED;tia sua, f&#xE9;cerit iniquit&#xE1;tem, ponam offend&#xED;culum coram eo; ipse mori&#xE9;tur, quia non commonu&#xED;sti eum: in pecc&#xE1;to suo mori&#xE9;tur, et non erunt in mem&#xF3;ria iust&#xED;tiae e&#xED;us, quas fecit; s&#xE1;nguinem vero e&#xED;us de manu tua requ&#xED;ram. Si autem tu common&#xFA;eris i&#xFA;stum, ut non peccet i&#xFA;stus, et ille non pecc&#xE1;verit, vivens vivet, quia commonu&#xED;sti eum et tu &#xE1;nimam tuam liber&#xE1;sti.&#x201D;</la></ligne>
</liturgia>
